torchfcpe/__init__.py
torchfcpe/mel_extractor.py
torchfcpe/mel_fn_librosa.py
torchfcpe/model_conformer_naive.py
torchfcpe/model_convnext.py
torchfcpe/models.py
torchfcpe/tools.py
torchfcpe/torch_interp.py
torchfcpe/assets/fcpe_c_v001.pt
torchfcpe-0.0.3.dist-info/LICENSE
torchfcpe-0.0.3.dist-info/METADATA
torchfcpe-0.0.3.dist-info/WHEEL
torchfcpe-0.0.3.dist-info/top_level.txt
torchfcpe-0.0.3.dist-info/RECORD
