Metadata-Version: 2.1
Name: torchfcpe
Version: 0.0.3
Summary: The official Pytorch implementation of Fast Context-based Pitch Estimation (FCPE)
Home-page: https://github.com/CNChTu/FCPE
Author: CNChTu
Author-email: 2921046558@qq.com
License: MIT
Keywords: pitch,audio,speech,music,pytorch,fcpe
Classifier: License :: OSI Approved :: MIT License
License-File: LICENSE
Requires-Dist: einops
Requires-Dist: local-attention
Requires-Dist: torch
Requires-Dist: torchaudio
Requires-Dist: numpy
